kivy_deps/__init__.py
kivy_deps/glew/__init__.py
kivy_deps.glew-0.3.1.data/data/share/glew/bin/glew32.dll
kivy_deps.glew-0.3.1.dist-info/METADATA
kivy_deps.glew-0.3.1.dist-info/WHEEL
kivy_deps.glew-0.3.1.dist-info/top_level.txt
kivy_deps.glew-0.3.1.dist-info/RECORD
