Metadata-Version: 2.1
Name: kivy_deps.glew
Version: 0.3.1
Summary: Repackaged binary dependency of Kivy.
Home-page: http://kivy.org/
Author: Kivy Team and other contributors
Author-email: kivy-dev@googlegroups.com
License: MIT
